{
  "theme": "tgr",
  "description": "TGR brand - Bold and energetic",
  "typography": {
    "headline1": {
      "fontFamily": "Helvetica Neue",
      "fontSize": "3.2rem",
      "lineHeight": "3.8rem",
      "letterSpacing": "0.1rem",
      "fontWeight": "700",
      "textTransform": "uppercase"
    },
    "headline2": {
      "fontFamily": "Helvetica Neue",
      "fontSize": "2.4rem",
      "lineHeight": "3rem",
      "letterSpacing": "0.06rem",
      "fontWeight": "700",
      "textTransform": "uppercase"
    },
    "headline3": {
      "fontFamily": "Helvetica Neue",
      "fontSize": "2rem",
      "lineHeight": "2.5rem",
      "letterSpacing": "0.04rem",
      "fontWeight": "700"
    },
    "text1": {
      "fontFamily": "Helvetica Neue",
      "fontSize": "1.5rem",
      "lineHeight": "2rem",
      "letterSpacing": "0.02rem",
      "fontWeight": "400"
    },
    "text2": {
      "fontFamily": "Helvetica Neue",
      "fontSize": "1.5rem",
      "lineHeight": "2rem",
      "fontWeight": "600"
    },
    "text3": {
      "fontFamily": "Helvetica Neue",
      "fontSize": "1.2rem",
      "lineHeight": "1.6rem",
      "fontWeight": "400"
    },
    "body1": {
      "fontFamily": "Helvetica Neue",
      "fontSize": "1.6rem",
      "lineHeight": "2.2rem",
      "fontWeight": "400"
    },
    "button1": {
      "fontFamily": "Helvetica Neue",
      "fontSize": "1.4rem",
      "lineHeight": "1.8rem",
      "letterSpacing": "0.06rem",
      "fontWeight": "700",
      "textTransform": "uppercase"
    },
    "caption1": {
      "fontFamily": "Helvetica Neue",
      "fontSize": "1.1rem",
      "lineHeight": "1.5rem",
      "fontWeight": "400"
    }
  },
  "colors": {
    "primary": "#ff6b35",
    "secondary": "#fff3e0",
    "accent": "#004e89",
    "success": "#2ecc71",
    "warning": "#f39c12",
    "danger": "#e74c3c",
    "info": "#3498db",
    "text": "#1a1a1a",
    "textSecondary": "#757575",
    "border": "#ffe0b2"
  }
}
